<annotation>
	<folder>pics</folder>
	<filename>frame_003.jpg</filename>
	<path>/home/wlk/Develop/gitDownload/yolo_tensorflow/DIYdata/pics/frame_003.jpg</path>
	<source>
		<database>Unknown</database>
	</source>
	<size>
		<width>1280</width>
		<height>720</height>
		<depth>3</depth>
	</size>
	<segmented>0</segmented>
	<object>
		<name>zhongtiww</name>
		<pose>Unspecified</pose>
		<truncated>0</truncated>
		<difficult>0</difficult>
		<bndbox>
			<xmin>8</xmin>
			<ymin>129</ymin>
			<xmax>989</xmax>
			<ymax>714</ymax>
		</bndbox>
	</object>
</annotation>
